{"id": "an+englishman+in+new+york+2009", "tmdb_id": 34937, "imdb_id": "tt0997057", "title": "An Englishman in New York", "original_title": "An Englishman in New York", "adult": "False", "belongs_to_collection": {}, "budget": "0", "genres": [{"id": 18, "name": "Drama"}], "homepage": "null", "original_language": "en", "overview": "Dramatization of the life of Quentin Crisp, author and self-proclaimed stylist, living out his golden years in NYC.", "popularity": "1.032342", "poster_path": "/AmvDPjBRla0Q3L0TpWDwWvsPA42.jpg", "production_companies": [{"name": "Leopard Drama", "id": 85638}], "production_countries": [{"iso_3166_1": "GB", "name": "United Kingdom"}], "release_date": "2009-04-27", "revenue": "0", "runtime": 75, "spoken_languages": [{"iso_639_1": "en", "name": "English"}], "status": "Released", "vote_average": "6.7", "vote_count": "9"}