{"id": "an+unmarried+woman+1978", "tmdb_id": 38731, "imdb_id": "tt0078444", "title": "An Unmarried Woman", "original_title": "An Unmarried Woman", "adult": "False", "belongs_to_collection": {}, "budget": "2515000", "genres": [{"id": 18, "name": "Drama"}, {"id": 10749, "name": "Romance"}, {"id": 35, "name": "Comedy"}], "homepage": "null", "original_language": "en", "overview": "A wealthy woman from Manhattan's Upper East Side struggles to deal with her new identity and her sexuality after her husband of 16 years leaves her for a younger woman.", "popularity": "1.148295", "poster_path": "/3HBWipP8b3joa4zjCeiwBT2F1IW.jpg", "production_companies": [{"name": "Twentieth Century Fox Film Corporation", "id": 306}], "production_countries": [{"iso_3166_1": "US", "name": "United States of America"}], "release_date": "1978-05-26", "revenue": "24000000", "runtime": 124, "spoken_languages": [{"iso_639_1": "en", "name": "English"}], "status": "Released", "vote_average": "6.1", "vote_count": "17"}