{"id": "big+pun+the+legacy+2009", "tmdb_id": 26465, "imdb_id": "tt1144866", "title": "Big Pun: The Legacy", "original_title": "Big Pun: The Legacy", "adult": "False", "belongs_to_collection": {}, "budget": "0", "genres": [{"id": 99, "name": "Documentary"}, {"id": 10402, "name": "Music"}], "homepage": "null", "original_language": "en", "overview": "His rhymes caught the attention of millions. His flow is un-matched by any. His story is captivating and triumphant. \"Big Pun: The Legacy\" chronicles the life of the Grammy Nominated artist \"Big Pun\" aka Christopher Rios, a Puerto Rican from the Bronx who made history by becoming the first Latino rapper to sell over a million records.", "popularity": "0.168673", "poster_path": "/hnYGiQuMGx0vjkPE7reraIzLOer.jpg", "production_companies": [], "production_countries": [], "release_date": "2009-09-01", "revenue": "0", "runtime": 95, "spoken_languages": [], "status": "Released", "vote_average": "5.8", "vote_count": "3"}