{"id": "eden+2012", "tmdb_id": 96599, "imdb_id": "tt1734433", "title": "Eden", "original_title": "Eden", "adult": "False", "belongs_to_collection": {}, "budget": "0", "genres": [{"id": 18, "name": "Drama"}], "homepage": "null", "original_language": "en", "overview": "The true story of Chong Kim who, as a young teen, was abducted into the sex trade, and the complicated moral choices she had to make in order to survive as her situation grew more desperate.", "popularity": "3.928695", "poster_path": "/75OshXJAVjSOonCCn6E08gH3ZwU.jpg", "production_companies": [{"name": "Eden Productions", "id": 22475}], "production_countries": [{"iso_3166_1": "US", "name": "United States of America"}], "release_date": "2012-03-11", "revenue": "0", "runtime": 98, "spoken_languages": [{"iso_639_1": "en", "name": "English"}, {"iso_639_1": "fr", "name": "Fran\u00e7ais"}, {"iso_639_1": "es", "name": "Espa\u00f1ol"}], "status": "Released", "vote_average": "6.5", "vote_count": "59"}