{"id": "last+winter+2012", "tmdb_id": 99880, "imdb_id": "tt1810798", "title": "Last Winter", "original_title": "L'hiver dernier", "adult": "False", "belongs_to_collection": {}, "budget": "0", "genres": [{"id": 53, "name": "Thriller"}], "homepage": "http://www.cccke.be", "original_language": "en", "overview": "A young farmer in Central France tries to sustain his spiritual connection to the land amid the crushing pressures of modern agriculture in this brooding drama.", "popularity": "0.776769", "poster_path": "/AaeCQnBNnIIFd1THZWRpcEBj2x5.jpg", "production_companies": [], "production_countries": [], "release_date": "2012-02-29", "revenue": "0", "runtime": 103, "spoken_languages": [{"iso_639_1": "fr", "name": "Fran\u00e7ais"}], "status": "Released", "vote_average": "5.5", "vote_count": "4"}