{"id": "lone+star+1996", "tmdb_id": 26748, "imdb_id": "tt0116905", "title": "Lone Star", "original_title": "Lone Star", "adult": "False", "belongs_to_collection": {}, "budget": "5000000", "genres": [{"id": 18, "name": "Drama"}, {"id": 9648, "name": "Mystery"}, {"id": 10749, "name": "Romance"}], "homepage": "null", "original_language": "en", "overview": "When the skeleton of his murdered predecessor is found, Sheriff Sam Deeds unearths many other long-buried secrets in his Texas border town.", "popularity": "9.069963", "poster_path": "/eSuuTqr5wmzWu4OCS51Qw0q6VrV.jpg", "production_companies": [{"name": "Castle Rock Entertainment", "id": 97}, {"name": "Columbia Pictures Corporation", "id": 441}, {"name": "Rio Dulce", "id": 11948}], "production_countries": [{"iso_3166_1": "US", "name": "United States of America"}], "release_date": "1996-06-21", "revenue": "13269963", "runtime": 135, "spoken_languages": [{"iso_639_1": "en", "name": "English"}, {"iso_639_1": "es", "name": "Espa\u00f1ol"}], "status": "Released", "vote_average": "6.9", "vote_count": "79"}