{"id": "peepli+live+2010", "tmdb_id": 44549, "imdb_id": "tt1447508", "title": "PEEPLI [Live]", "original_title": "PEEPLI [Live]", "adult": "False", "belongs_to_collection": {}, "budget": "2270000", "genres": [{"id": 18, "name": "Drama"}, {"id": 35, "name": "Comedy"}], "homepage": "http://www.peeplilivethefilm.com/", "original_language": "hi", "overview": "Natha a poor farmer from Peepli village in the heart of rural India is about to lose his plot of land due to an unpaid bank loan. A quick fix to the problem is the a government program that aids the families of indebted farmers who have committed suicide. As a means of survival Farmer Natha can choose to die. His brother is happy to push him towards this unique 'honour' but Natha is reluctant. Local elections are around the corner and what might have been another unnoticed event turns into a 'cause celebre' with everyone wanting a piece of the action. Political bigwigs, high-ranking bureaucrats, local henchmen and the ever-zealous media descend upon sleepy Peepli to stake their claim. The question on everyone's lips - \"Will he or Won't he?\" As the mania escalates, nobody seems to care how Natha really feels.", "popularity": "2.927226", "poster_path": "/qZBRbiaHaOO9tbMl35gApkZ28.jpg", "production_companies": [], "production_countries": [{"iso_3166_1": "IN", "name": "India"}], "release_date": "2010-08-13", "revenue": "6900000", "runtime": 104, "spoken_languages": [{"iso_639_1": "hi", "name": "\u0939\u093f\u0928\u094d\u0926\u0940"}, {"iso_639_1": "en", "name": "English"}], "status": "Released", "vote_average": "7.7", "vote_count": "17"}