{"id": "saps+at+sea+1940", "tmdb_id": 46260, "imdb_id": "tt0033022", "title": "Saps at Sea", "original_title": "Saps at Sea", "adult": "False", "belongs_to_collection": {}, "budget": "0", "genres": [{"id": 35, "name": "Comedy"}], "homepage": "null", "original_language": "en", "overview": "Stan and Ollie work in a horn factory. Ollie starts having violent fits every time he hears a horn. His doctor prescribes a restful sea voyage. Mayhem ensues.", "popularity": "0.691018", "poster_path": "/2U0HKcT0iqmtezOxW0gViBB3Zfq.jpg", "production_companies": [{"name": "Hal Roach Studios", "id": 2159}], "production_countries": [{"iso_3166_1": "US", "name": "United States of America"}], "release_date": "1940-05-03", "revenue": "0", "runtime": 57, "spoken_languages": [{"iso_639_1": "en", "name": "English"}], "status": "Released", "vote_average": "6.7", "vote_count": "17"}