{"id": "the+final+season+2007", "tmdb_id": 15669, "imdb_id": "tt0449018", "title": "The Final Season", "original_title": "The Final Season", "adult": "False", "belongs_to_collection": {}, "budget": "0", "genres": [{"id": 18, "name": "Drama"}], "homepage": "null", "original_language": "en", "overview": "True story of Kent Stock, who in the early 90's, gives up a job and ditches his wedding plans to take over as head coach as the Norway High School baseball team. Kent must win over his players and convince them and himself that he can fill their former coach's shoes and that they can go out winners. In the summer of 1991 Norway High's baseball tradition ended on a triumphant but sombre note.", "popularity": "1.053739", "poster_path": "/lvVQlc0cuN4XPVsK3MplO4FOLKp.jpg", "production_companies": [], "production_countries": [], "release_date": "2007-10-12", "revenue": "0", "runtime": 119, "spoken_languages": [], "status": "Released", "vote_average": "5.2", "vote_count": "14"}