{"id": "travellers+and+magicians+2003", "tmdb_id": 37232, "imdb_id": "tt0378906", "title": "Travellers and Magicians", "original_title": "Travellers and Magicians", "adult": "False", "belongs_to_collection": {}, "budget": "0", "genres": [{"id": 12, "name": "Adventure"}, {"id": 18, "name": "Drama"}, {"id": 10769, "name": "Foreign"}], "homepage": "http://www.travellersandmagicians.com/", "original_language": "en", "overview": "A young government official, named Dondup, who is smitten with America (he even has a denim gho) dreams of escaping there while stuck in a beautiful but isolated village. He hopes to connect in the U.S. with a visa out of the country. He misses the one bus out of town to Thimphu, however, and is forced to hitchhike and walk along the Lateral Road to the west, accompanied by an apple seller, a Buddhist monk with his ornate, dragon-headed dramyin, a drunk, a widowed rice paper maker, and his beautiful daughter, Sonam.", "popularity": "0.635804", "poster_path": "/4yev0a0Opkjv2NbyjHXpTDTd2Lb.jpg", "production_companies": [{"name": "Prayer Flag Pictures", "id": 72591}], "production_countries": [{"iso_3166_1": "BT", "name": "Bhutan"}, {"iso_3166_1": "GB", "name": "United Kingdom"}, {"iso_3166_1": "AU", "name": "Australia"}], "release_date": "2003-09-09", "revenue": "0", "runtime": 108, "spoken_languages": [{"iso_639_1": "dz", "name": ""}], "status": "Released", "vote_average": "6.8", "vote_count": "9"}