{"id": "what+would+jesus+buy+2007", "tmdb_id": 16117, "imdb_id": "tt0939681", "title": "What Would Jesus Buy?", "original_title": "What Would Jesus Buy?", "adult": "False", "belongs_to_collection": {}, "budget": "0", "genres": [{"id": 99, "name": "Documentary"}], "homepage": "null", "original_language": "en", "overview": "A serious docu-comedy about the commercialization of Christmas. What Would Jesus Buy? follows Reverend Billy and the Church of Stop Shopping Gospel Choir as they go on a cross-country mission to save Christmas from the Shopocalypse: the end of mankind from consumerism, over-consumption and the fires of eternal debt!", "popularity": "0.249382", "poster_path": "/UJTFRKmihynJvOvYE4n2vg0Rko.jpg", "production_companies": [{"name": "Palisades Pictures", "id": 3950}, {"name": "Warrior Poets", "id": 3951}], "production_countries": [{"iso_3166_1": "US", "name": "United States of America"}], "release_date": "2007-03-11", "revenue": "0", "runtime": 91, "spoken_languages": [{"iso_639_1": "en", "name": "English"}], "status": "Released", "vote_average": "7.7", "vote_count": "3"}