{"id": "whatever+1998", "tmdb_id": 102304, "imdb_id": "tt0140688", "title": "Whatever", "original_title": "Whatever", "adult": "False", "belongs_to_collection": {}, "budget": "0", "genres": [{"id": 18, "name": "Drama"}], "homepage": "http://www.sonyclassics.com/whatever/whatever.html", "original_language": "en", "overview": "A teen faces her impending adulthood in the carefree sex and drug revolution years of the early 80's prior to fears of AIDS. She lives with her bitter, divorced mother and her sadistic kid brother. Looking forward to a life based on her passion for art, she nevertheless gets in with the partying crowd which causes her to miss deadlines and poor grades which jeopardizes her future. Ultimately she ends up losing her virginity to an older artist wanna-be who she has had a longstanding crush on.", "popularity": "0.291914", "poster_path": "/dkVIN6LND6vTCw0MTnuRAbcEXJn.jpg", "production_companies": [{"name": "Circle Films", "id": 11273}, {"name": "DuArt", "id": 20049}, {"name": "Anyway Productions", "id": 40240}], "production_countries": [{"iso_3166_1": "US", "name": "United States of America"}], "release_date": "1998-07-10", "revenue": "0", "runtime": 112, "spoken_languages": [{"iso_639_1": "en", "name": "English"}], "status": "Released", "vote_average": "8.3", "vote_count": "2"}