{"id": "whirlygirl+2006", "tmdb_id": 17236, "imdb_id": "tt0364745", "title": "Whirlygirl", "original_title": "Whirlygirl", "adult": "False", "belongs_to_collection": {}, "budget": "0", "genres": [{"id": 10749, "name": "Romance"}, {"id": 18, "name": "Drama"}], "homepage": "null", "original_language": "en", "overview": "After a run in with a hot exotic dancer one wintry night straight-laced prep school student James will find himself on the ride of his life. Risking his future he follows this mysterious woman to New York City - ditching school dodging cops and partying at hot nightclubs along the way.", "popularity": "4.364247", "poster_path": "/vfgYyizaEKa37XvmLTaZhY7GgEV.jpg", "production_companies": [{"name": "Tig Productions", "id": 335}, {"name": "All the Way Round", "id": 3274}, {"name": "Beacon Classics", "id": 54517}], "production_countries": [{"iso_3166_1": "US", "name": "United States of America"}], "release_date": "2006-05-02", "revenue": "0", "runtime": 99, "spoken_languages": [{"iso_639_1": "en", "name": "English"}], "status": "Released", "vote_average": "5.5", "vote_count": "10"}