{"id": "wild+at+heart+1990", "tmdb_id": 483, "imdb_id": "tt0100935", "title": "Wild at Heart", "original_title": "Wild at Heart", "adult": "False", "belongs_to_collection": {}, "budget": "9500000", "genres": [{"id": 35, "name": "Comedy"}, {"id": 80, "name": "Crime"}, {"id": 53, "name": "Thriller"}], "homepage": "null", "original_language": "en", "overview": "Young lovers Sailor and Lula run from the variety of weirdos that Lula's mom has hired to kill Sailor.", "popularity": "8.528622", "poster_path": "/d4fbQjSSBd4FPyAROln1skafChr.jpg", "production_companies": [{"name": "Samuel Goldwyn", "id": 261}], "production_countries": [{"iso_3166_1": "US", "name": "United States of America"}], "release_date": "1990-05-01", "revenue": "14560247", "runtime": 124, "spoken_languages": [{"iso_639_1": "en", "name": "English"}], "status": "Released", "vote_average": "7.0", "vote_count": "341"}