{"id": "a+visitor+to+a+museum+1989", "tmdb_id": 73922, "imdb_id": "tt0173024", "title": "A Visitor to a Museum", "original_title": "\u041f\u043e\u0441\u0435\u0442\u0438\u0442\u0435\u043b\u044c \u043c\u0443\u0437\u0435\u044f", "adult": "False", "belongs_to_collection": {}, "budget": "0", "genres": [{"id": 18, "name": "Drama"}], "homepage": "null", "original_language": "ru", "overview": "It is the future, the world is in ruins and a large portion of the population consists of deformed mutants living in reservations. In this world a man decides to spend his vacation visiting the ruins of a museum that is now buried under the sea.", "popularity": "0.658363", "poster_path": "/qmEKdTKTi0LbhXpy3jaeAK1zuQw.jpg", "production_companies": [], "production_countries": [], "release_date": "1989-03-14", "revenue": "0", "runtime": 136, "spoken_languages": [{"iso_639_1": "ru", "name": "P\u0443\u0441\u0441\u043a\u0438\u0439"}], "status": "Released", "vote_average": "7.6", "vote_count": "8"}