{"id": "angelas+ashes+1999", "tmdb_id": 10397, "imdb_id": "tt0145653", "title": "Angela's Ashes", "original_title": "Angela's Ashes", "adult": "False", "belongs_to_collection": {}, "budget": "25", "genres": [{"id": 18, "name": "Drama"}], "homepage": "null", "original_language": "en", "overview": "Based on the best selling autobiography by Irish expat Frank McCourt, Angela's Ashes follows the experiences of young Frankie and his family as they try against all odds to escape the poverty endemic in the slums of pre-war Limerick. The film opens with the family in Brooklyn, but following the death of one of Frankie's siblings, they return home, only to find the situation there even worse. Prejudice against Frankie's Northern Irish father makes his search for employment in the Republic difficult despite his having fought for the IRA, and when he does find money, he spends the money on drink.", "popularity": "4.496585", "poster_path": "/k5RM5J582tviQSXhYkKvYnQCkmc.jpg", "production_companies": [{"name": "Paramount Pictures", "id": 4}, {"name": "Universal Pictures", "id": 33}], "production_countries": [{"iso_3166_1": "IE", "name": "Ireland"}, {"iso_3166_1": "US", "name": "United States of America"}], "release_date": "1999-12-25", "revenue": "13", "runtime": 145, "spoken_languages": [{"iso_639_1": "en", "name": "English"}], "status": "Released", "vote_average": "7.0", "vote_count": "59"}