{"id": "deception+2008", "tmdb_id": 13018, "imdb_id": "tt0800240", "title": "Deception", "original_title": "Deception", "adult": "False", "belongs_to_collection": {}, "budget": "25000000", "genres": [{"id": 53, "name": "Thriller"}], "homepage": "null", "original_language": "en", "overview": "As a corporate auditor who works in a number of different offices, Jonathan McQuarry wanders without an anchor among New York's power brokers. A chance meeting with charismatic lawyer Wyatt Bose leads to Jonathan's introduction to The List, an underground sex club. Jonathan begins an affair with a woman known only as S, who introduces Jonathan to a world of treachery and murder.", "popularity": "7.720729", "poster_path": "/mpRwbg5yZFdyeYCZ0eaEpKnhDsG.jpg", "production_companies": [{"name": "Kanzaman", "id": 4169}, {"name": "Rifkin-Eberts", "id": 4307}, {"name": "Dune Entertainment III", "id": 6332}, {"name": "Seed Productions", "id": 9076}, {"name": "Media Rights Capital (MRC)", "id": 86655}], "production_countries": [{"iso_3166_1": "US", "name": "United States of America"}], "release_date": "2008-04-24", "revenue": "17741298", "runtime": 107, "spoken_languages": [{"iso_639_1": "en", "name": "English"}], "status": "Released", "vote_average": "5.7", "vote_count": "200"}