{"id": "flu+2013", "tmdb_id": 200085, "imdb_id": "tt2351310", "title": "Flu", "original_title": "\uac10\uae30", "adult": "False", "belongs_to_collection": {}, "budget": "0", "genres": [{"id": 28, "name": "Action"}, {"id": 18, "name": "Drama"}, {"id": 878, "name": "Science Fiction"}], "homepage": "null", "original_language": "ko", "overview": "Infected through the respiratory system, there is a new kind of disease that kills in 36 hours once infected. The people of the city struggle to survive this. The worst epidemic ever seen is sweeping through Bundang, the suburb of Seoul. After smuggling illegal immigrants into the country, Byung-woo dies from an unknown virus. Soon after that, the same symptoms are plaguing scores of residents in Bundang.", "popularity": "4.522582", "poster_path": "/6umLdWyHyeu7J9KDQVmjFHUb3KZ.jpg", "production_companies": [{"name": "iLoveCinema", "id": 20695}, {"name": "iFilm Co.", "id": 20696}], "production_countries": [{"iso_3166_1": "KR", "name": "South Korea"}], "release_date": "2013-08-14", "revenue": "0", "runtime": 122, "spoken_languages": [{"iso_639_1": "ko", "name": "\ud55c\uad6d\uc5b4/\uc870\uc120\ub9d0"}], "status": "Released", "vote_average": "7.0", "vote_count": "83"}