{"id": "freeze+frame+2004", "tmdb_id": 12612, "imdb_id": "tt0363095", "title": "Freeze Frame", "original_title": "Freeze Frame", "adult": "False", "belongs_to_collection": {}, "budget": "0", "genres": [{"id": 53, "name": "Thriller"}, {"id": 18, "name": "Drama"}, {"id": 80, "name": "Crime"}], "homepage": "null", "original_language": "en", "overview": "Sean Veil is an ultra paranoid murder suspect who takes to filming himself round the clock to provide an alibi, just in case he's ever accused of another crime. Problems arise however when the police do come calling and the one tape that can prove his innocence has mysteriously disappeared.", "popularity": "2.352193", "poster_path": "/pLh6xchx7iVBU6H64Za4Wp6qeDW.jpg", "production_companies": [], "production_countries": [{"iso_3166_1": "GB", "name": "United Kingdom"}, {"iso_3166_1": "IE", "name": "Ireland"}], "release_date": "2004-05-01", "revenue": "0", "runtime": 99, "spoken_languages": [{"iso_639_1": "en", "name": "English"}], "status": "Released", "vote_average": "6.9", "vote_count": "18"}