{"id": "ice+castles+2010", "tmdb_id": 33570, "imdb_id": "tt1411276", "title": "Ice Castles", "original_title": "Ice Castles", "adult": "False", "belongs_to_collection": {}, "budget": "0", "genres": [{"id": 18, "name": "Drama"}], "homepage": "null", "original_language": "en", "overview": "Alexis Winston is a young girl who dreams of becoming a champion figure skater. While practicing, Alexis suffers a terrible accident that takes her sight and threatens to destroy her dreams. In the midst of feeling sorry for herself she falls in love with a handsome young man named Nick who (with help from her family) helps her to realize that she can still fulfill her dreams.", "popularity": "1.579212", "poster_path": "/h5qCr25Ir4aCQJfsncSLBf8voxe.jpg", "production_companies": [{"name": "Jaffe/Braunstein Films", "id": 5003}, {"name": "Stage 6 Films", "id": 11341}, {"name": "RCR Media Group", "id": 17837}], "production_countries": [{"iso_3166_1": "CA", "name": "Canada"}, {"iso_3166_1": "US", "name": "United States of America"}], "release_date": "2010-02-09", "revenue": "0", "runtime": 95, "spoken_languages": [{"iso_639_1": "en", "name": "English"}], "status": "Released", "vote_average": "6.2", "vote_count": "13"}