{"id": "knight+and+day+2010", "tmdb_id": 37834, "imdb_id": "tt1013743", "title": "Knight and Day", "original_title": "Knight and Day", "adult": "False", "belongs_to_collection": {}, "budget": "117000000", "genres": [{"id": 28, "name": "Action"}, {"id": 35, "name": "Comedy"}], "homepage": "http://www.knightanddaymovie.com", "original_language": "en", "overview": "A fugitive couple goes on a glamorous and sometimes deadly adventure where nothing and no one \u2013 even themselves \u2013 are what they seem. Amid shifting alliances and unexpected betrayals, they race across the globe, with their survival ultimately hinging on the battle of truth vs. trust.", "popularity": "12.758942", "poster_path": "/aHEpzwXvMtIEMBE13tWXS5oHZ7d.jpg", "production_companies": [{"name": "Tree Line Films", "id": 84}, {"name": "Twentieth Century Fox Film Corporation", "id": 306}, {"name": "Dune Entertainment", "id": 444}, {"name": "Regency Enterprises", "id": 508}, {"name": "Pink Machine", "id": 21845}], "production_countries": [{"iso_3166_1": "US", "name": "United States of America"}], "release_date": "2010-06-15", "revenue": "261930431", "runtime": 109, "spoken_languages": [{"iso_639_1": "en", "name": "English"}, {"iso_639_1": "de", "name": "Deutsch"}, {"iso_639_1": "es", "name": "Espa\u00f1ol"}], "status": "Released", "vote_average": "5.9", "vote_count": "1583"}