{"id": "outside+the+law+2010", "tmdb_id": 47904, "imdb_id": "tt1229381", "title": "Outside the Law", "original_title": "Hors-la-loi", "adult": "False", "belongs_to_collection": {}, "budget": "30000000", "genres": [{"id": 28, "name": "Action"}, {"id": 18, "name": "Drama"}, {"id": 36, "name": "History"}, {"id": 10752, "name": "War"}], "homepage": "http://www.horslaloi-lefilm.com/", "original_language": "fr", "overview": "After losing their family home in Algeria in the 1920s, three brothers and their mother are scattered across the globe. Messaoud joins the French army fighting in Indochina; Abdelkader becomes a leader of the Algerian independence movement in France and Sa\u00efd moves to Paris to make his fortune in the shady clubs and boxing halls of Pigalle.", "popularity": "1.170864", "poster_path": "/n2P3mbuXGIZ1M3PeIGq6rYQuxuk.jpg", "production_companies": [{"name": "France 3 Cin\u00e9ma", "id": 591}, {"name": "Studio Canal", "id": 5870}, {"name": "Agence Alg\u00e9rienne pour le Rayonnement Culturel (AARC)", "id": 7461}, {"name": "EPTV", "id": 7462}, {"name": "Kiss Films", "id": 7464}, {"name": "Novak Production", "id": 7465}, {"name": "Radio T\u00e9l\u00e9vision Belge Francophone (RTBF)", "id": 7466}], "production_countries": [{"iso_3166_1": "FR", "name": "France"}, {"iso_3166_1": "DZ", "name": "Algeria"}, {"iso_3166_1": "BE", "name": "Belgium"}], "release_date": "2010-09-21", "revenue": "0", "runtime": 137, "spoken_languages": [{"iso_639_1": "ar", "name": "\u0627\u0644\u0639\u0631\u0628\u064a\u0629"}, {"iso_639_1": "fr", "name": "Fran\u00e7ais"}], "status": "Released", "vote_average": "6.5", "vote_count": "20"}