{"id": "the+prize+of+peril+1983", "tmdb_id": 51259, "imdb_id": "tt0084540", "title": "The Prize of Peril", "original_title": "Le prix du danger", "adult": "False", "belongs_to_collection": {}, "budget": "0", "genres": [{"id": 28, "name": "Action"}, {"id": 18, "name": "Drama"}, {"id": 878, "name": "Science Fiction"}], "homepage": "null", "original_language": "fr", "overview": "In a futuristic society, contestants pit their survival skills against each other in a fight to the death for cash prizes, and the contest is aired live on television.", "popularity": "0.672756", "poster_path": "/dum5ii6bXXsizqGu7hvXv9f1Xdg.jpg", "production_companies": [{"name": "TF1 Films Production", "id": 3823}, {"name": "Avala Film", "id": 5940}, {"name": "Top n\u00b01", "id": 29485}, {"name": "Swabie Production", "id": 78414}], "production_countries": [{"iso_3166_1": "FR", "name": "France"}, {"iso_3166_1": "RS", "name": "Serbia"}], "release_date": "1983-01-25", "revenue": "0", "runtime": 100, "spoken_languages": [{"iso_639_1": "fr", "name": "Fran\u00e7ais"}], "status": "Released", "vote_average": "5.5", "vote_count": "5"}