{"id": "the+ref+1994", "tmdb_id": 10872, "imdb_id": "tt0110955", "title": "The Ref", "original_title": "The Ref", "adult": "False", "belongs_to_collection": {}, "budget": "11000000", "genres": [{"id": 35, "name": "Comedy"}], "homepage": "null", "original_language": "en", "overview": "A cat burglar is forced to take a bickering, dysfunctional family hostage on Christmas Eve.", "popularity": "5.868677", "poster_path": "/njp8Vyx77uCJsGIwnIfu4zfBwFR.jpg", "production_companies": [{"name": "Touchstone Pictures", "id": 9195}, {"name": "Don Simpson/Jerry Bruckheimer Films", "id": 10288}], "production_countries": [{"iso_3166_1": "US", "name": "United States of America"}], "release_date": "1994-03-09", "revenue": "11439193", "runtime": 97, "spoken_languages": [{"iso_639_1": "en", "name": "English"}], "status": "Released", "vote_average": "6.7", "vote_count": "99"}