{"id": "welcome+to+the+dollhouse+1995", "tmdb_id": 11446, "imdb_id": "tt0114906", "title": "Welcome to the Dollhouse", "original_title": "Welcome to the Dollhouse", "adult": "False", "belongs_to_collection": {}, "budget": "0", "genres": [{"id": 35, "name": "Comedy"}, {"id": 18, "name": "Drama"}], "homepage": "null", "original_language": "en", "overview": "An unattractive 7th grader struggles to cope with suburban life as the middle child with un-attentive parents and bullies at school.", "popularity": "5.14056", "poster_path": "/jvxLLHwpK52ZJUusd2RJv8oLHUJ.jpg", "production_companies": [], "production_countries": [{"iso_3166_1": "US", "name": "United States of America"}], "release_date": "1995-05-24", "revenue": "0", "runtime": 88, "spoken_languages": [{"iso_639_1": "en", "name": "English"}], "status": "Released", "vote_average": "6.9", "vote_count": "103"}