{"id": "a+bronx+tale+1993", "tmdb_id": 1607, "imdb_id": "tt0106489", "title": "A Bronx Tale", "original_title": "A Bronx Tale", "adult": "False", "belongs_to_collection": {}, "budget": "22000000", "genres": [{"id": 18, "name": "Drama"}, {"id": 80, "name": "Crime"}], "homepage": "null", "original_language": "en", "overview": "Set in the Bronx during the tumultuous 1960s, an adolescent boy is torn between his honest, working-class father and a violent yet charismatic crime boss. Complicating matters is the youngster's growing attraction - forbidden in his neighborhood - for a beautiful black girl.", "popularity": "6.115628", "poster_path": "/wlYIwDwk53R4h0uMnpK1NAhHqdg.jpg", "production_companies": [{"name": "HBO Films", "id": 7429}, {"name": "Savoy Pictures", "id": 11308}], "production_countries": [{"iso_3166_1": "US", "name": "United States of America"}], "release_date": "1993-09-14", "revenue": "17287898", "runtime": 121, "spoken_languages": [{"iso_639_1": "en", "name": "English"}, {"iso_639_1": "it", "name": "Italiano"}], "status": "Released", "vote_average": "7.4", "vote_count": "447"}