{"id": "archangel+1990", "tmdb_id": 85559, "imdb_id": "tt0099053", "title": "Archangel", "original_title": "Archangel", "adult": "False", "belongs_to_collection": {}, "budget": "0", "genres": [{"id": 35, "name": "Comedy"}, {"id": 18, "name": "Drama"}, {"id": 10749, "name": "Romance"}, {"id": 10752, "name": "War"}], "homepage": "null", "original_language": "en", "overview": "A surrealistic film in which a strangely assorted group of people come together in the Russian Arctic at the height of the revolution and World War One.", "popularity": "0.170087", "poster_path": "/re6l1aTLbi3OwNYgIbLEsHg0FVd.jpg", "production_companies": [{"name": "Cinephile", "id": 94447}, {"name": "Ordnance Pictures", "id": 94448}], "production_countries": [{"iso_3166_1": "CA", "name": "Canada"}], "release_date": "1990-09-01", "revenue": "0", "runtime": 90, "spoken_languages": [{"iso_639_1": "en", "name": "English"}], "status": "Released", "vote_average": "6.0", "vote_count": "12"}