{"id": "beau+travail+2000", "tmdb_id": 14626, "imdb_id": "tt0209933", "title": "Beau Travail", "original_title": "Beau Travail", "adult": "False", "belongs_to_collection": {}, "budget": "0", "genres": [{"id": 18, "name": "Drama"}], "homepage": "null", "original_language": "fr", "overview": "Foreign Legion officer, Galoup, recalls his once glorious life, leading troops in the Gulf of Djibouti. His existence there was happy, strict and regimented, but the arrival of a promising young recruit, Sentain, plants the seeds of jealousy in Galoup's mind. He feels compelled to stop him from coming to the attention of the commandant who he admires, but who ignores him. Ultimately, his jealousy leads to the destruction of both Sentain and himself.", "popularity": "2.336209", "poster_path": "/yVEWdkztcxgWD0JxuH2U1KLXUya.jpg", "production_companies": [{"name": "La Sept-Arte", "id": 11332}, {"name": "Tana\u00efs Productions", "id": 75482}, {"name": "S.M. Films", "id": 75483}], "production_countries": [{"iso_3166_1": "FR", "name": "France"}], "release_date": "2000-05-03", "revenue": "0", "runtime": 90, "spoken_languages": [{"iso_639_1": "fr", "name": "Fran\u00e7ais"}, {"iso_639_1": "it", "name": "Italiano"}, {"iso_639_1": "ru", "name": "P\u0443\u0441\u0441\u043a\u0438\u0439"}], "status": "Released", "vote_average": "7.2", "vote_count": "35"}