{"id": "california+split+1974", "tmdb_id": 32044, "imdb_id": "tt0071269", "title": "California Split", "original_title": "California Split", "adult": "False", "belongs_to_collection": {}, "budget": "0", "genres": [{"id": 35, "name": "Comedy"}, {"id": 18, "name": "Drama"}], "homepage": "null", "original_language": "en", "overview": "A down on his luck gambler links up with free spirit Elliot Gould at first to have some fun on, but then gets into debt when Gould takes an unscheduled trip to Tijuana. As a final act of desperation, he pawns most of his possessions and goes to Reno for the poker game of a lifetime. A film set mainly in casinos and races, as the two win and lose (but mainly win), get robbed, and get blind drunk.", "popularity": "3.148851", "poster_path": "/AslOvKRXy4tKcmmkDm1GFHTgOdF.jpg", "production_companies": [{"name": "Columbia Pictures Corporation", "id": 441}, {"name": "Won World", "id": 41310}, {"name": "Spelling Goldberg", "id": 41311}], "production_countries": [{"iso_3166_1": "US", "name": "United States of America"}], "release_date": "1974-08-07", "revenue": "0", "runtime": 108, "spoken_languages": [{"iso_639_1": "en", "name": "English"}], "status": "Released", "vote_average": "6.5", "vote_count": "26"}