{"id": "dead+times+1964", "tmdb_id": 69559, "imdb_id": "tt0294959", "title": "Dead Times", "original_title": "Les temps morts", "adult": "False", "belongs_to_collection": {}, "budget": "0", "genres": [{"id": 16, "name": "Animation"}, {"id": 18, "name": "Drama"}], "homepage": "null", "original_language": "fr", "overview": "What is man? Man makes war, man kills man, man hunts, man is executed. A montage mixing original drawings by Topor, original shots and stock shots that ironically analyze what man is. Early Rene Laloux film", "popularity": "0.474695", "poster_path": "/gclPrshXz3nKQeR3wSOF0G7ECgs.jpg", "production_companies": [{"name": "Como Films", "id": 46570}], "production_countries": [{"iso_3166_1": "FR", "name": "France"}], "release_date": "1964-12-01", "revenue": "0", "runtime": 10, "spoken_languages": [{"iso_639_1": "fr", "name": "Fran\u00e7ais"}], "status": "Released", "vote_average": "8.4", "vote_count": "5"}