{"id": "drained+2006", "tmdb_id": 40860, "imdb_id": "tt0489458", "title": "Drained", "original_title": "O Cheiro do Ralo", "adult": "False", "belongs_to_collection": {}, "budget": "0", "genres": [{"id": 35, "name": "Comedy"}, {"id": 10769, "name": "Foreign"}], "homepage": "null", "original_language": "pt", "overview": "A pawn shop proprietor buys used goods from desperate locals--as much to play perverse power games as for his own livelihood, but when the perfect rump and a backed-up toilet enter his life, he loses all control.", "popularity": "0.623789", "poster_path": "/pAmJFKsuLKIcUNzkv34QllUheL7.jpg", "production_companies": [{"name": "RT Features", "id": 30666}, {"name": "Primo Filmes", "id": 33792}, {"name": "Tristero Filmes", "id": 81036}, {"name": "Branca Filmes", "id": 93181}, {"name": "Gera\u00e7\u00e3o Conte\u00fado", "id": 93182}], "production_countries": [{"iso_3166_1": "BR", "name": "Brazil"}], "release_date": "2006-09-27", "revenue": "0", "runtime": 112, "spoken_languages": [{"iso_639_1": "pt", "name": "Portugu\u00eas"}], "status": "Released", "vote_average": "6.7", "vote_count": "18"}