{"id": "earthquake+1974", "tmdb_id": 11123, "imdb_id": "tt0071455", "title": "Earthquake", "original_title": "Earthquake", "adult": "False", "belongs_to_collection": {}, "budget": "7000000", "genres": [{"id": 28, "name": "Action"}, {"id": 18, "name": "Drama"}, {"id": 53, "name": "Thriller"}], "homepage": "null", "original_language": "en", "overview": "Earthquake is a 1974 American disaster film that achieved huge box-office success, continuing the disaster film genre of the 1970s where recognizable all-star casts attempt to survive life or death situations. The plot concerns the struggle for survival after a catastrophic earthquake destroys most of the city of Los Angeles, California.", "popularity": "6.657792", "poster_path": "/dlMwsiC1jtJ2hRmIJOZCDjr2xRy.jpg", "production_companies": [{"name": "Universal Pictures", "id": 33}, {"name": "The Filmakers Group", "id": 12277}], "production_countries": [{"iso_3166_1": "US", "name": "United States of America"}], "release_date": "1974-11-15", "revenue": "79666653", "runtime": 123, "spoken_languages": [{"iso_639_1": "en", "name": "English"}], "status": "Released", "vote_average": "5.6", "vote_count": "76"}