{"id": "easy+street+1917", "tmdb_id": 47650, "imdb_id": "tt0007880", "title": "Easy Street", "original_title": "Easy Street", "adult": "False", "belongs_to_collection": {}, "budget": "0", "genres": [{"id": 35, "name": "Comedy"}], "homepage": "null", "original_language": "en", "overview": "When Charlie the Tramp wanders into a mission he is smitten by Edna and puts back the collection box which he has taken. Reformed, he becomes a policeman and is assigned to rough-and-tumble Easy Street. Unable to trick or beat Eric the Tough, he puts Eric's head in a gas pipe and anesthetizes him. A hero, he now helps many poor people living on Easy Street. Eric escapes jail, Edna is kidnapped, but Charlie (recharged after sitting on a doper's needle) conquers all. Easy Street is transformed as is Eric.", "popularity": "1.795202", "poster_path": "/iwC1esWImnV0CvAB7j3KQ9nXxG4.jpg", "production_companies": [{"name": "Lone Star Corporation", "id": 930}], "production_countries": [{"iso_3166_1": "US", "name": "United States of America"}], "release_date": "1917-01-22", "revenue": "0", "runtime": 24, "spoken_languages": [{"iso_639_1": "en", "name": "English"}], "status": "Released", "vote_average": "7.0", "vote_count": "31"}