{"id": "enid+2009", "tmdb_id": 43711, "imdb_id": "tt1397265", "title": "Enid", "original_title": "Enid", "adult": "False", "belongs_to_collection": {}, "budget": "0", "genres": [{"id": 18, "name": "Drama"}], "homepage": "null", "original_language": "en", "overview": "Edwardian child Enid Blyton begins to tell stories to her brothers as an escape from their parents' rows before the father deserts the family...", "popularity": "0.660874", "poster_path": "/jOIWj4dhkIGh7Hk9tkcDGfERYn7.jpg", "production_companies": [], "production_countries": [{"iso_3166_1": "US", "name": "United States of America"}], "release_date": "2009-11-16", "revenue": "0", "runtime": 82, "spoken_languages": [{"iso_639_1": "en", "name": "English"}], "status": "Released", "vote_average": "6.2", "vote_count": "6"}