{"id": "grandmother+2009", "tmdb_id": 72985, "imdb_id": "tt1496792", "title": "Grandmother", "original_title": "Lola", "adult": "False", "belongs_to_collection": {}, "budget": "0", "genres": [{"id": 18, "name": "Drama"}], "homepage": "null", "original_language": "tl", "overview": "Lola Sepa's grandson has been killed by a cell phone snatcher. Despite being devastated by the sudden violence, she must bear the burden of making the funeral arrangements. She and her family are poor, and there is not enough money for the coffin nor the legal pursuit against the suspected murderer. But the elderly woman is ready to even seek a bank loan to assure both a proper burial and justice for her beloved grandson. Lola Puring is committed to getting her grandson Mateo out of jail, although he has been accused of senselessly murdering Lola Sepa's grandson. But the poor aged woman doesn't have the bail money. Each time she visits her grandson in prison to bring him proper meals, it breaks her heart to see him wasting away behind bars with countless others. At the first court hearing, the two grandmothers must face one another. Both frail and poor, each is determined to do everything necessary for her grandson. The future of the case is dependent on grandmotherly love...", "popularity": "0.723687", "poster_path": "/fP8NfK8r0r8WsycaauXJviJ3jtx.jpg", "production_companies": [{"name": "Centerstage Productions", "id": 7008}, {"name": "Swift Productions", "id": 23812}], "production_countries": [{"iso_3166_1": "PH", "name": "Philippines"}, {"iso_3166_1": "FR", "name": "France"}], "release_date": "2009-09-23", "revenue": "0", "runtime": 110, "spoken_languages": [{"iso_639_1": "tl", "name": ""}], "status": "Released", "vote_average": "7.0", "vote_count": "4"}