{"id": "heathers+1988", "tmdb_id": 2640, "imdb_id": "tt0097493", "title": "Heathers", "original_title": "Heathers", "adult": "False", "belongs_to_collection": {}, "budget": "0", "genres": [{"id": 53, "name": "Thriller"}, {"id": 35, "name": "Comedy"}, {"id": 18, "name": "Drama"}], "homepage": "null", "original_language": "en", "overview": "A girl who halfheartedly tries to be part of the \"in crowd\" of her school meets a rebel who teaches her a more devious way to play social politics: by killing the popular kids.", "popularity": "13.311827", "poster_path": "/38DHopfWHrWqYjphcBeAxOomled.jpg", "production_companies": [{"name": "New World Pictures", "id": 1950}, {"name": "Cinemarque Entertainment", "id": 10170}], "production_countries": [{"iso_3166_1": "US", "name": "United States of America"}], "release_date": "1988-10-01", "revenue": "1108462", "runtime": 102, "spoken_languages": [{"iso_639_1": "en", "name": "English"}, {"iso_639_1": "it", "name": "Italiano"}], "status": "Released", "vote_average": "7.3", "vote_count": "387"}