{"id": "martha+marcy+may+marlene+2011", "tmdb_id": 50837, "imdb_id": "tt1441326", "title": "Martha Marcy May Marlene", "original_title": "Martha Marcy May Marlene", "adult": "False", "belongs_to_collection": {}, "budget": "0", "genres": [{"id": 18, "name": "Drama"}, {"id": 53, "name": "Thriller"}], "homepage": "http://www.foxsearchlight.com/marthamarcymaymarlene/", "original_language": "en", "overview": "After several years of living with a cult, Martha finally escapes and calls her estranged sister, Lucy, for help. Martha finds herself at the quiet Connecticut home Lucy shares with her new husband, Ted, but the memories of what she experienced in the cult make peace hard to find. As flashbacks continue to torment her, Martha fails to shake a terrible sense of dread, especially in regard to the cult's manipulative leader.", "popularity": "7.665011", "poster_path": "/f68uBuxkEfesHmw5eJxFOnNalTY.jpg", "production_companies": [{"name": "Cunningham & Maybach Films", "id": 10056}, {"name": "FilmHaven Entertainment", "id": 10057}, {"name": "BorderLine Films", "id": 10058}, {"name": "This Is That Productions", "id": 10059}], "production_countries": [{"iso_3166_1": "US", "name": "United States of America"}], "release_date": "2011-10-21", "revenue": "3538446", "runtime": 101, "spoken_languages": [{"iso_639_1": "en", "name": "English"}], "status": "Released", "vote_average": "6.7", "vote_count": "278"}