{"id": "metal+brothers+2012", "tmdb_id": 163590, "imdb_id": "tt2256749", "title": "Metal Brothers", "original_title": "Mammas pojkar", "adult": "False", "belongs_to_collection": {}, "budget": "0", "genres": [{"id": 35, "name": "Comedy"}], "homepage": "null", "original_language": "sv", "overview": "Br\u00f6derna H\u00e5rdrock is a film about two brothers who are planning a heavy metal convention in their sleepy village. Their mother, the village priest, worries about them and wants them to settle down and have families. A young female teacher and line dance instructor in the village sets both their hearts beating faster and, unaware of each other's feelings, they enter a battle to win her affections.", "popularity": "0.520486", "poster_path": "/jmVmphDPGnLuHsYDol9XulWmnDk.jpg", "production_companies": [{"name": "BOB Film Sweden AB", "id": 3792}], "production_countries": [{"iso_3166_1": "SE", "name": "Sweden"}], "release_date": "2012-12-24", "revenue": "0", "runtime": 100, "spoken_languages": [{"iso_639_1": "sv", "name": "svenska"}], "status": "Released", "vote_average": "4.5", "vote_count": "10"}