{"id": "raise+your+voice+2004", "tmdb_id": 14024, "imdb_id": "tt0361696", "title": "Raise Your Voice", "original_title": "Raise Your Voice", "adult": "False", "belongs_to_collection": {}, "budget": "15000000", "genres": [{"id": 10402, "name": "Music"}, {"id": 18, "name": "Drama"}, {"id": 10749, "name": "Romance"}], "homepage": "http://www.newline.com/properties/raiseyourvoice.html", "original_language": "en", "overview": "Raise Your Voice is a coming-of-age story centered around a small-town singer, brokenhearted by the death of her brother in a car crash, who had secretly submitted her for a summer session at a performing arts academy in Los Angeles. In the performing arts academy, she experiences a whole new way of life in the big city, far from the small town lifestyle she's used to.", "popularity": "4.387004", "poster_path": "/b1fdAQC87xpxKzfP1akrrmsDR6R.jpg", "production_companies": [{"name": "New Line Cinema", "id": 12}, {"name": "FilmEngine", "id": 816}, {"name": "Brookwell-McNamara Entertainment", "id": 3235}, {"name": "ChickFlick Productions", "id": 15312}], "production_countries": [{"iso_3166_1": "US", "name": "United States of America"}], "release_date": "2004-08-10", "revenue": "14867514", "runtime": 103, "spoken_languages": [{"iso_639_1": "en", "name": "English"}, {"iso_639_1": "fr", "name": "Fran\u00e7ais"}], "status": "Released", "vote_average": "6.0", "vote_count": "221"}