{"id": "slipstream+1989", "tmdb_id": 22379, "imdb_id": "tt0098350", "title": "Slipstream", "original_title": "Slipstream", "adult": "False", "belongs_to_collection": {}, "budget": "0", "genres": [{"id": 878, "name": "Science Fiction"}, {"id": 12, "name": "Adventure"}], "homepage": "null", "original_language": "en", "overview": "Slipstream is a 1989 post-apocalyptic science fiction adventure film. The plot has an emphasis on aviation and contains many common science-fiction themes, such as taking place in a dystopian future in which the landscape of the Earth itself has been changed and is windswept by storms of great power. There are also numerous sub-plots, such as free will and humanity amongst artificial intelligence.", "popularity": "1.697976", "poster_path": "/m86WfIjcYHx1QjEbK2HSTMIeNKX.jpg", "production_companies": [], "production_countries": [], "release_date": "1989-06-22", "revenue": "0", "runtime": 102, "spoken_languages": [{"iso_639_1": "en", "name": "English"}], "status": "Released", "vote_average": "4.2", "vote_count": "16"}