{"id": "the+old+man+and+the+sea+1958", "tmdb_id": 11331, "imdb_id": "tt0052027", "title": "The Old Man and the Sea", "original_title": "The Old Man and the Sea", "adult": "False", "belongs_to_collection": {}, "budget": "0", "genres": [{"id": 12, "name": "Adventure"}, {"id": 18, "name": "Drama"}], "homepage": "null", "original_language": "en", "overview": "Based on one of Hemingway's most famous works, it centers upon Santiago, an aging, down on his luck Cuban fisherman. After catching nothing for nearly 3 months, he hooks a huge Marlin and struggles to land it far out in the Gulf Stream.", "popularity": "1.728104", "poster_path": "/cZw8zKKwEOUrSNo14Nk91kz82gm.jpg", "production_companies": [{"name": "Warner Bros.", "id": 6194}, {"name": "Leland Hayward Productions", "id": 18875}], "production_countries": [{"iso_3166_1": "US", "name": "United States of America"}], "release_date": "1958-10-07", "revenue": "0", "runtime": 86, "spoken_languages": [{"iso_639_1": "en", "name": "English"}], "status": "Released", "vote_average": "6.0", "vote_count": "25"}