{"id": "the+man+who+laughs+1928", "tmdb_id": 27517, "imdb_id": "tt0019130", "title": "The Man Who Laughs", "original_title": "The Man Who Laughs", "adult": "False", "belongs_to_collection": {}, "budget": "0", "genres": [{"id": 18, "name": "Drama"}, {"id": 27, "name": "Horror"}], "homepage": "null", "original_language": "en", "overview": "Gwynplaine, son of Lord Clancharlie, has a permanent smile carved on his face by the King, in revenge for Gwynplaine's father's treachery. Gwynplaine is adopted by a travelling showman and becomes a popular idol. He falls in love with the blind Dea. The king dies, and his evil jester tries to destroy or corrupt Gwynplaine.", "popularity": "2.571104", "poster_path": "/8eVqvmUFRPp7nXrxVVcVYJ5pfbN.jpg", "production_companies": [{"name": "Universal Pictures", "id": 33}], "production_countries": [{"iso_3166_1": "US", "name": "United States of America"}], "release_date": "1928-04-27", "revenue": "0", "runtime": 110, "spoken_languages": [], "status": "Released", "vote_average": "7.4", "vote_count": "32"}