{"id": "the+pokrovsky+gates+1982", "tmdb_id": 37176, "imdb_id": "tt0083465", "title": "The Pokrovsky Gates", "original_title": "\u041f\u043e\u043a\u0440\u043e\u0432\u0441\u043a\u0438\u0435 \u0432\u043e\u0440\u043e\u0442\u0430", "adult": "False", "belongs_to_collection": {}, "budget": "0", "genres": [{"id": 35, "name": "Comedy"}, {"id": 18, "name": "Drama"}, {"id": 10749, "name": "Romance"}], "homepage": "null", "original_language": "ru", "overview": "Stories from the lives of the tenants of the Moscow's communal apartment: Kostik, who is a college student, lives with his aunt while studying; Arkady Velyurov who is a performing artist; Khobotovs, who are a divorced couple; and Sava, who is Margarita Khobotov's new fianc\u00e9. All these people live in one apartment and their lives constantly touch each other's.", "popularity": "0.651047", "poster_path": "/fLvr6oh5TkxNc3fNnVLpcnwoAUs.jpg", "production_companies": [{"name": "Mosfilm", "id": 5120}], "production_countries": [{"iso_3166_1": "RU", "name": "Russia"}], "release_date": "1982-01-01", "revenue": "0", "runtime": 140, "spoken_languages": [{"iso_639_1": "ru", "name": "P\u0443\u0441\u0441\u043a\u0438\u0439"}], "status": "Released", "vote_average": "6.5", "vote_count": "11"}