{"id": "things+you+can+tell+just+by+looking+at+her+1999", "tmdb_id": 20067, "imdb_id": "tt0210358", "title": "Things You Can Tell Just by Looking at Her", "original_title": "Things You Can Tell Just by Looking at Her", "adult": "False", "belongs_to_collection": {}, "budget": "0", "genres": [{"id": 18, "name": "Drama"}, {"id": 10749, "name": "Romance"}], "homepage": "http://www.mgm.com/thingsyoucantell/", "original_language": "en", "overview": "In California, a group of women struggle with personal problems as their paths intertwine in unexpected ways. Dr. Elaine Keener, the sole caretaker for her aging mother, turns to tarot card reader Christine for spiritual aid. Christine grapples with her own angst due to her lover's debilitating illness. Meanwhile, a bank manager deals with an unwanted pregnancy, two sisters pursue romantic interests and a housewife gets back into the dating game.", "popularity": "4.166882", "poster_path": "/gHWFif5RVZf2PHy6JbHxkdqXYoR.jpg", "production_companies": [{"name": "Franchise Pictures", "id": 1403}, {"name": "Avnet/Kerner Productions", "id": 34998}, {"name": "LTZ II Inc.", "id": 35712}], "production_countries": [{"iso_3166_1": "US", "name": "United States of America"}], "release_date": "1999-10-28", "revenue": "0", "runtime": 109, "spoken_languages": [{"iso_639_1": "en", "name": "English"}], "status": "Released", "vote_average": "6.4", "vote_count": "14"}