{"id": "valmont+1989", "tmdb_id": 37606, "imdb_id": "tt0098575", "title": "Valmont", "original_title": "Valmont", "adult": "False", "belongs_to_collection": {}, "budget": "33000000", "genres": [{"id": 18, "name": "Drama"}, {"id": 10749, "name": "Romance"}], "homepage": "null", "original_language": "en", "overview": "Set in Baroque France, a scheming widow and her lover make a bet regarding the corruption of a recently married woman. The lover, Valmont, bets that he can seduce her, even though she is an honorable woman. If he wins, he can have his lover to do as he will. However, in the process of seducing the married woman, Valmont falls in love. Based on the same novel as \"Dangerous Liaisons.\"", "popularity": "8.40852", "poster_path": "/ez9OFvq9Ayzuwb8jroCHY2Z06Xb.jpg", "production_companies": [{"name": "Renn Productions", "id": 82}, {"name": "Timothy Burrill Productions", "id": 8131}], "production_countries": [{"iso_3166_1": "FR", "name": "France"}, {"iso_3166_1": "US", "name": "United States of America"}], "release_date": "1989-11-17", "revenue": "1132112", "runtime": 137, "spoken_languages": [{"iso_639_1": "en", "name": "English"}], "status": "Released", "vote_average": "6.7", "vote_count": "50"}